pelican/plugins/mau_reader/__init__.py
pelican/plugins/mau_reader/mau_reader.py
pelican/plugins/mau_reader/test_mau_reader.py
pelican_mau_reader-4.0.0.dist-info/METADATA
pelican_mau_reader-4.0.0.dist-info/WHEEL
pelican_mau_reader-4.0.0.dist-info/RECORD
