Metadata-Version: 2.1
Name: pelican-mau-reader
Version: 4.0.0
Summary: Pelican plugin that converts Mau-formatted content into HTML
Keywords: pelican,plugin
Author-Email: Leonardo Giordani <giordani.leonardo@gmail.com>, Justin Mayer <entroP@gmail.com>
License: MIT
Classifier: Development Status :: 5 - Production/Stable
Classifier: Environment :: Console
Classifier: Framework :: Pelican
Classifier: Framework :: Pelican :: Plugins
Classifier: Intended Audience :: End Users/Desktop
Classifier: License :: OSI Approved :: MIT License
Classifier: Operating System :: OS Independent
Classifier: Programming Language :: Python :: 3
Classifier: Programming Language :: Python :: 3.8
Classifier: Programming Language :: Python :: 3.9
Classifier: Programming Language :: Python :: 3.10
Classifier: Programming Language :: Python :: 3.11
Classifier: Programming Language :: Python :: 3.12
Classifier: Topic :: Internet :: WWW/HTTP
Classifier: Topic :: Software Development :: Libraries :: Python Modules
Project-URL: Homepage, https://github.com/pelican-plugins/mau-reader
Project-URL: Issue tracker, https://github.com/pelican-plugins/mau-reader/issues
Project-URL: Funding, https://donate.getpelican.com/
Requires-Python: <4.0,>=3.8.1
Requires-Dist: pelican>=4.5
Requires-Dist: mau<5.0.0,>=4.0.0
Requires-Dist: mau-html-visitor>=2.0.0
Requires-Dist: markdown>=3.4; extra == "markdown"
Provides-Extra: markdown
